transceiver/__init__.py
transceiver/core.py
transceiver/utils.py
transceiver-0.1.3.dist-info/METADATA
transceiver-0.1.3.dist-info/WHEEL
transceiver-0.1.3.dist-info/licenses/LICENSE
transceiver-0.1.3.dist-info/RECORD
