Metadata-Version: 2.3
Name: transceiver
Version: 0.1.3
Summary: Transceiver is a python library that swiftly exchanges fundamental data structures, specifically numpy arrays, between processes, optimizing AI inference tasks that utilize ComfyUI.
Project-URL: Homepage, https://github.com/nat-chan/transceiver
Project-URL: Issues, https://github.com/nat-chan/transceiver/issues
Author-email: nat-chan <ogino.natsuki.tm@alumni.tsukuba.ac.jp>
License-File: LICENSE
Classifier: License :: OSI Approved :: MIT License
Classifier: Operating System :: OS Independent
Classifier: Programming Language :: Python :: 3
Requires-Python: >=3.10
Requires-Dist: numpy>=1.26.4
